README.md
setup.py
taxi_bexio/__init__.py
taxi_bexio/backend.py
taxi_bexio.egg-info/PKG-INFO
taxi_bexio.egg-info/SOURCES.txt
taxi_bexio.egg-info/dependency_links.txt
taxi_bexio.egg-info/entry_points.txt
taxi_bexio.egg-info/requires.txt
taxi_bexio.egg-info/top_level.txt