Metadata-Version: 1.2
Name: taxi-bexio
Version: 1.0.1
Summary: Bexio backend for Taxi
Home-page: https://github.com/alexandreblin/taxi-bexio
Author: Alexandre Blin
Author-email: alexandre@blin.fr
License: wtfpl
Platform: UNKNOWN
Classifier: Programming Language :: Python :: 3.6
Classifier: Programming Language :: Python :: 3.7
Classifier: Programming Language :: Python :: 3.8
Requires-Python: >=3.6
